transkun/Data.py
transkun/Evaluation.py
transkun/LayersTransformer.py
transkun/Layers_ablation.py
transkun/ModelTransformer.py
transkun/Model_ablation.py
transkun/SyncBN.py
transkun/TrainUtil.py
transkun/Util.py
transkun/__init__.py
transkun/computeMetrics.py
transkun/createDatasetMaestro.py
transkun/crfMinimalExample.py
transkun/plotDeviation.py
transkun/train.py
transkun/transcribe.py
transkun/CRF/NeuralSemiCRFInterval.py
transkun/CRF/__init__.py
transkun/pretrained/2.0.conf
transkun/pretrained/2.0.pt
transkun/pretrained/__init__.py
transkun-2.0.1.dist-info/LICENSE
transkun-2.0.1.dist-info/METADATA
transkun-2.0.1.dist-info/WHEEL
transkun-2.0.1.dist-info/entry_points.txt
transkun-2.0.1.dist-info/top_level.txt
transkun-2.0.1.dist-info/RECORD
