Metadata-Version: 2.1
Name: transkun
Version: 2.0.1
Summary: Yet another tool for automatic piano transcription
Home-page: https://github.com/Yujia-Yan/Skipping-The-Frame-Level
Author: Yujia Yan
Classifier: Programming Language :: Python :: 3
Classifier: License :: OSI Approved :: MIT License
Classifier: Operating System :: OS Independent
Requires-Python: >=3.6
License-File: LICENSE
Requires-Dist: ncls
Requires-Dist: pretty-midi
Requires-Dist: scipy
Requires-Dist: torchaudio
Requires-Dist: torch
Requires-Dist: mir-eval
Requires-Dist: pydub
Requires-Dist: seaborn
Requires-Dist: matplotlib
Requires-Dist: tensorboard
Requires-Dist: tqdm
Requires-Dist: torch-optimizer
Requires-Dist: sox
Requires-Dist: soxr
Requires-Dist: moduleconf
